amazon_lex_bot_deploy/__init__.py
amazon_lex_bot_deploy/amazon_lex_bot_deploy.py
amazon_lex_bot_deploy/examples/BookTrip_Export.json
amazon_lex_bot_deploy/examples/OrderFlowers_Export.json
amazon_lex_bot_deploy/examples/ScheduleAppointment_Export.json
amazon_lex_bot_deploy-0.1.7.data/scripts/lex-bot-deploy
amazon_lex_bot_deploy-0.1.7.data/scripts/lex-bot-get-schema
amazon_lex_bot_deploy-0.1.7.dist-info/LICENSE
amazon_lex_bot_deploy-0.1.7.dist-info/METADATA
amazon_lex_bot_deploy-0.1.7.dist-info/WHEEL
amazon_lex_bot_deploy-0.1.7.dist-info/top_level.txt
amazon_lex_bot_deploy-0.1.7.dist-info/RECORD
