Metadata-Version: 2.1
Name: amazon-lex-bot-deploy
Version: 0.1.7
Summary: The sample code provides a deploy function and an executable to easily deploy an Amazon Lex bot based on a Lex Schema file.
Home-page: https://github.com/aws-samples/amazon_lex_bot_deploy
Author: Martin Schade
Author-email: amazon-lex-bot-deploy@amazon.com
License: MIT-0 license
Keywords: amazon_lex_bot_deploy Amazon Lex Automation Deploy CICD
Platform: UNKNOWN
Classifier: Development Status :: 2 - Pre-Alpha
Classifier: Intended Audience :: Developers
Classifier: License :: OSI Approved :: MIT License
Classifier: Natural Language :: English
Classifier: Programming Language :: Python :: 2
Classifier: Programming Language :: Python :: 2.7
Classifier: Programming Language :: Python :: 3
Classifier: Programming Language :: Python :: 3.4
Classifier: Programming Language :: Python :: 3.5
Classifier: Programming Language :: Python :: 3.6
Classifier: Programming Language :: Python :: 3.7
Requires-Dist: boto3
Requires-Dist: botocore
Requires-Dist: tenacity
